Metadata-Version: 2.1
Name: ortu
Version: 0.6.0
Summary: Route table updater for Oracle Cloud Infrastructure
Home-page: https://github.com/ITD27M01/oci-route-table-updater
Author: itd27m01
Author-email: igortiunov@gmail.com
License: MIT
Platform: UNKNOWN
Classifier: Programming Language :: Python :: 3
Classifier: Programming Language :: Python :: 3.8
Classifier: License :: OSI Approved :: MIT License
Classifier: Intended Audience :: Developers
Classifier: Operating System :: OS Independent
